LICENSE
MANIFEST.in
README.rst
setup.cfg
setup.py
resolos/__init__.py
resolos/__main__.py
resolos/archive.py
resolos/check.py
resolos/conda.py
resolos/config.py
resolos/env.py
resolos/error.py
resolos/exception.py
resolos/init.py
resolos/interface.py
resolos/job.py
resolos/logging.py
resolos/platform.py
resolos/remote.py
resolos/remote_configuration.py
resolos/shell.py
resolos/unison.py
resolos/version.py
resolos.egg-info/PKG-INFO
resolos.egg-info/SOURCES.txt
resolos.egg-info/dependency_links.txt
resolos.egg-info/entry_points.txt
resolos.egg-info/not-zip-safe
resolos.egg-info/requires.txt
resolos.egg-info/top_level.txt
resolos/storage/__init__.py
resolos/storage/yareta.py
resolos/unison/default.prf