Metadata-Version: 2.1
Name: resolos
Version: 0.5.0
Summary: Reproducible research made easy
Home-page: https://github.com/nuvolos-cloud/resolos
Author: Alphacruncher
Author-email: support@nuvolos.cloud
License: MIT
Platform: UNKNOWN
License-File: LICENSE
